{
  "parent": "minecraft:story/wood",
  "display": {
    "icon": {
      "item": "minecraft:crafting_table"
    },
    "title": {
      "translate": "It's Crafting Time!"
    },
    "description": {
      "translate": "Make a Crafting Table"
    },
    "frame": "task",
    "show_toast": true,
    "announce_to_chat": true,
    "hidden": false
  },
  "criteria": {
    "get_wood": {
      "trigger": "minecraft:inventory_changed",
      "conditions": {
        "items": [
          {
            "item": "minecraft:crafting_table"
          }
        ]
      }
    }
  },
  "requirements": [
    [
      "get_wood"
    ]
  ]
}